steam_idle
