Metadata-Version: 1.1
Name: steam-idle
Version: 1.0
Summary: Idle Steam apps/games for card drops
Home-page: https://github.com/jayme-github/steam_idle
Author: Jayme
Author-email: tuxnet@gmail.com
License: GNU Affero General Public License v3
Keywords: steam
Platform: any
Classifier: Development Status :: 5 - Production/Stable
Classifier: License :: OSI Approved :: GNU Affero General Public License v3
Classifier: Operating System :: OS Independent
Classifier: Programming Language :: Python
